sqliteparser/__init__.py
sqliteparser/ast.py
sqliteparser/exceptions.py
sqliteparser/lexer.py
sqliteparser/parser.py
sqliteparser/utils.py
sqliteparser-0.6.1.dist-info/LICENSE
sqliteparser-0.6.1.dist-info/METADATA
sqliteparser-0.6.1.dist-info/WHEEL
sqliteparser-0.6.1.dist-info/top_level.txt
sqliteparser-0.6.1.dist-info/RECORD
