Metadata-Version: 2.1
Name: sqliteparser
Version: 0.6.1
Summary: A parser for SQLite's dialect of SQL
Home-page: UNKNOWN
Author: Ian Fisher
Author-email: iafisher@fastmail.com
License: MIT
Project-URL: Source, https://github.com/iafisher/sqliteparser
Platform: UNKNOWN
Classifier: Programming Language :: Python :: 3
Classifier: Programming Language :: SQL
Classifier: License :: OSI Approved :: MIT License
Classifier: Natural Language :: English
Classifier: Topic :: Database
Requires-Dist: attrs (>=20.3.0)
